typecheck/__init__.py
typecheck/test_typecheck_decorator.py
typecheck/typecheck_decorator.py
typecheck_decorator_stable-1.0.dist-info/DESCRIPTION.rst
typecheck_decorator_stable-1.0.dist-info/METADATA
typecheck_decorator_stable-1.0.dist-info/metadata.json
typecheck_decorator_stable-1.0.dist-info/RECORD
typecheck_decorator_stable-1.0.dist-info/top_level.txt
typecheck_decorator_stable-1.0.dist-info/WHEEL
