Metadata-Version: 2.0
Name: typecheck-decorator-stable
Version: 1.0
Summary: flexible explicit type checking of function arguments (Python3-only)
Home-page: http://github.com/prechelt/typecheck-decorator-stable
Author: Dmitry Dvoinikov, Lutz Prechelt
Author-email: prechelt@inf.fu-berlin.de
License: BSD License
Keywords: type-checking
Platform: UNKNOWN
Classifier: License :: OSI Approved :: BSD License
Classifier: Development Status :: 5 - Production/Stable
Classifier: Intended Audience :: Developers
Classifier: Topic :: Software Development :: Quality Assurance
Classifier: Topic :: Software Development :: Documentation
Classifier: Programming Language :: Python :: 3
Classifier: Programming Language :: Python :: 3.3
Classifier: Programming Language :: Python :: 3.4
